xpipeline/__init__.py
xpipeline/cli.py
xpipeline/constants.py
xpipeline/core.py
xpipeline/irods.py
xpipeline/lsqr.py
xpipeline/test_core.py
xpipeline/test_lsqr.py
xpipeline/types.py
xpipeline/utils.py
xpipeline/version.py
xpipeline/commands/__init__.py
xpipeline/commands/aligned_cutouts.py
xpipeline/commands/base.py
xpipeline/commands/clio_calibrate.py
xpipeline/commands/clio_split.py
xpipeline/commands/collect_dataset.py
xpipeline/commands/combine.py
xpipeline/commands/compute_sky_model.py
xpipeline/commands/copy_test.py
xpipeline/commands/diagnostic.py
xpipeline/commands/eval_klip.py
xpipeline/commands/evaluate.py
xpipeline/commands/inject.py
xpipeline/commands/klip.py
xpipeline/commands/local_klip.py
xpipeline/commands/make_templates.py
xpipeline/commands/scale_templates.py
xpipeline/commands/sky_subtract.py
xpipeline/commands/stack.py
xpipeline/commands/subtract_starlight.py
xpipeline/commands/summarize_grid.py
xpipeline/commands/update_headers.py
xpipeline/commands/vapp_trap.py
xpipeline/pipelines/__init__.py
xpipeline/ref/__init__.py
xpipeline/ref/magellan.py
xpipeline/ref/naco_betapic_preproc_absil2013_gonzalez2017.npz
xpipeline/ref/clio/3.9um_Clio.dat
xpipeline/ref/clio/__init__.py
xpipeline/ref/clio/clio_pupil_mask.fits
xpipeline/ref/clio/vAPP_phase_bottom.fits
xpipeline/ref/clio/vAPP_phase_top.fits
xpipeline/tasks/__init__.py
xpipeline/tasks/characterization.py
xpipeline/tasks/data_quality.py
xpipeline/tasks/detector.py
xpipeline/tasks/improc.py
xpipeline/tasks/iofits.py
xpipeline/tasks/learning.py
xpipeline/tasks/obs_table.py
xpipeline/tasks/regions.py
xpipeline/tasks/sky_model.py
xpipeline/tasks/starlight_subtraction.py
xpipeline/tasks/test_characterization.py
xpipeline/tasks/test_common.py
xpipeline/tasks/test_improc.py
xpipeline/tasks/test_learning.py
xpipeline/tasks/test_starlight_subtraction.py
xpipeline/tasks/test_vapp.py
xpipeline/tasks/vapp.py
xpipeline-0.0.1.dist-info/LICENSE
xpipeline-0.0.1.dist-info/METADATA
xpipeline-0.0.1.dist-info/WHEEL
xpipeline-0.0.1.dist-info/entry_points.txt
xpipeline-0.0.1.dist-info/top_level.txt
xpipeline-0.0.1.dist-info/RECORD
